anlogger/__init__.py
anlogger/logger.py
anlogger-1.2.1.dist-info/LICENSE
anlogger-1.2.1.dist-info/METADATA
anlogger-1.2.1.dist-info/WHEEL
anlogger-1.2.1.dist-info/top_level.txt
anlogger-1.2.1.dist-info/RECORD
