Metadata-Version: 2.1
Name: anlogger
Version: 1.2.1
Summary: Module to assist in setting up logging.
Author-email: Antti Nilsson <muut.py@antion.fi>
Classifier: Programming Language :: Python :: 3
Classifier: License :: OSI Approved :: MIT License
Classifier: Operating System :: OS Independent
Requires-Python: >=3.7
License-File: LICENSE
